cz_base.py
commitizen_cz_base-0.2.0.dist-info/LICENSE
commitizen_cz_base-0.2.0.dist-info/METADATA
commitizen_cz_base-0.2.0.dist-info/WHEEL
commitizen_cz_base-0.2.0.dist-info/entry_points.txt
commitizen_cz_base-0.2.0.dist-info/top_level.txt
commitizen_cz_base-0.2.0.dist-info/RECORD
