Metadata-Version: 2.1
Name: commitizen-cz-base
Version: 0.2.0
Summary: Commitizen configuration for base Angewandte projects
License: Apache Software License 2.0
Classifier: Programming Language :: Python :: 3
Requires-Python: >=3.7
License-File: LICENSE
Requires-Dist: commitizen >=3.0.0
